<annotation>
  <folder>Downloads</folder>
  <filename>14956.png</filename>
  <size>
    <width>1280</width>
    <height>720</height>
    <depth>3</depth>
  </size>
  <segmented>0</segmented>
  <object>
    <name>Green</name>
    <pose>Unspecified</pose>
    <occluded>False</occluded>
    <difficult>0</difficult>
    <bndbox>
      <xmin>745.480057451</xmin>
      <ymin>310.7673050849</ymin>
      <xmax>753.0069825802</xmax>
      <ymax>330.4820808196</ymax>
    </bndbox>
  </object>
  <object>
    <name>Green</name>
    <pose>Unspecified</pose>
    <occluded>False</occluded>
    <difficult>0</difficult>
    <bndbox>
      <xmin>603.589406881</xmin>
      <ymin>274.5794652254</ymin>
      <xmax>609.714001031</xmax>
      <ymax>297.5977483277</ymax>
    </bndbox>
  </object>
  <object>
    <name>Green</name>
    <pose>Unspecified</pose>
    <occluded>False</occluded>
    <difficult>0</difficult>
    <bndbox>
      <xmin>653.6179780703</xmin>
      <ymin>276.8151839761</ymin>
      <xmax>659.5013237361</xmax>
      <ymax>293.1286150685</ymax>
    </bndbox>
  </object>
  <object>
    <name>Green</name>
    <pose>Unspecified</pose>
    <occluded>False</occluded>
    <difficult>0</difficult>
    <bndbox>
      <xmin>406.1482130706</xmin>
      <ymin>323.5679870992</ymin>
      <xmax>413.0726980648</xmax>
      <ymax>342.0249283009</ymax>
    </bndbox>
  </object>
</annotation>
