<annotation>
  <folder>Downloads</folder>
  <filename>32040.png</filename>
  <size>
    <width>1280</width>
    <height>720</height>
    <depth>3</depth>
  </size>
  <segmented>0</segmented>
  <object>
    <name>RedLeft</name>
    <pose>Unspecified</pose>
    <occluded>False</occluded>
    <difficult>0</difficult>
    <bndbox>
      <xmin>488.0525088576</xmin>
      <ymin>203.3465075449</ymin>
      <xmax>500.2288227893</xmax>
      <ymax>232.5910811842</ymax>
    </bndbox>
  </object>
  <object>
    <name>Green</name>
    <pose>Unspecified</pose>
    <occluded>False</occluded>
    <difficult>0</difficult>
    <bndbox>
      <xmin>591.2647171312</xmin>
      <ymin>203.3393685809</ymin>
      <xmax>604.6995752228</xmax>
      <ymax>232.6605044029</ymax>
    </bndbox>
  </object>
  <object>
    <name>Green</name>
    <pose>Unspecified</pose>
    <occluded>False</occluded>
    <difficult>0</difficult>
    <bndbox>
      <xmin>822.9314777689</xmin>
      <ymin>270.716141299</ymin>
      <xmax>835.1715948992</xmax>
      <ymax>295.1551279246</ymax>
    </bndbox>
  </object>
  <object>
    <name>Green</name>
    <pose>Unspecified</pose>
    <occluded>False</occluded>
    <difficult>0</difficult>
    <bndbox>
      <xmin>1016.9057065335</xmin>
      <ymin>232.397134057</ymin>
      <xmax>1031.9614289533</xmax>
      <ymax>250.1399597135</ymax>
    </bndbox>
  </object>
  <object>
    <name>RedLeft</name>
    <pose>Unspecified</pose>
    <occluded>False</occluded>
    <difficult>0</difficult>
    <bndbox>
      <xmin>119.1598325252</xmin>
      <ymin>288.9536506269</ymin>
      <xmax>130.990269218</xmax>
      <ymax>317.7440384443</ymax>
    </bndbox>
  </object>
</annotation>
